xtgen/__init__.py
xtgen/cmd_line.py
xtgen/config.py
xtgen/default_config.toml
xtgen/help.py
xtgen/keras_gen.py
xtgen/pytorch_gen.py
xtgen/scanner.py
xtgen/utils.py
xtgen/assets/keras_assets/mnist/README.md
xtgen/assets/keras_assets/mnist/requirements.txt
xtgen/assets/keras_assets/mnist/train.py
xtgen/assets/pytorch_assets/mnist/README.md
xtgen/assets/pytorch_assets/mnist/requirements.txt
xtgen/assets/pytorch_assets/mnist/train.py
xtgen/assets/pytorch_assets/snli/README.md
xtgen/assets/pytorch_assets/snli/model.py
xtgen/assets/pytorch_assets/snli/requirements.txt
xtgen/assets/pytorch_assets/snli/train.py
xtgen/assets/pytorch_assets/snli/util.py
xtgen-0.0.10.data/scripts/run_xtgen.py
xtgen-0.0.10.data/scripts/xtgen
xtgen-0.0.10.data/scripts/xtgen.bat
xtgen-0.0.10.dist-info/METADATA
xtgen-0.0.10.dist-info/WHEEL
xtgen-0.0.10.dist-info/top_level.txt
xtgen-0.0.10.dist-info/RECORD
